[
  {
    "ContainingType": "ApiQUIZZ.Controllers.AlternativasController",
    "Method": "GetAlternativas",
    "RelativePath": "api/Alternativas",
    "HttpMethod": "GET",
    "IsController": true,
    "Order": 0,
    "Parameters": [],
    "ReturnTypes": [
      {
        "Type": "System.Collections.Generic.IEnumerable\u00601[[ApiQUIZZ.Models.Alternativa, ApiQUIZZ, Version=1.0.0.0, Culture=neutral, PublicKeyToken=null]]",
        "MediaTypes": [
          "text/plain",
          "application/json",
          "text/json"
        ],
        "StatusCode": 200
      }
    ]
  },
  {
    "ContainingType": "ApiQUIZZ.Controllers.AlternativasController",
    "Method": "PostAlternativa",
    "RelativePath": "api/Alternativas",
    "HttpMethod": "POST",
    "IsController": true,
    "Order": 0,
    "Parameters": [
      {
        "Name": "alternativa",
        "Type": "ApiQUIZZ.Models.Alternativa",
        "IsRequired": true
      }
    ],
    "ReturnTypes": [
      {
        "Type": "ApiQUIZZ.Models.Alternativa",
        "MediaTypes": [
          "text/plain",
          "application/json",
          "text/json"
        ],
        "StatusCode": 200
      }
    ]
  },
  {
    "ContainingType": "ApiQUIZZ.Controllers.AlternativasController",
    "Method": "GetAlternativa",
    "RelativePath": "api/Alternativas/{id}",
    "HttpMethod": "GET",
    "IsController": true,
    "Order": 0,
    "Parameters": [
      {
        "Name": "id",
        "Type": "System.Int32",
        "IsRequired": true
      }
    ],
    "ReturnTypes": [
      {
        "Type": "ApiQUIZZ.Models.Alternativa",
        "MediaTypes": [
          "text/plain",
          "application/json",
          "text/json"
        ],
        "StatusCode": 200
      }
    ]
  },
  {
    "ContainingType": "ApiQUIZZ.Controllers.AlternativasController",
    "Method": "PutAlternativa",
    "RelativePath": "api/Alternativas/{id}",
    "HttpMethod": "PUT",
    "IsController": true,
    "Order": 0,
    "Parameters": [
      {
        "Name": "id",
        "Type": "System.Int32",
        "IsRequired": true
      },
      {
        "Name": "alternativa",
        "Type": "ApiQUIZZ.Models.Alternativa",
        "IsRequired": true
      }
    ],
    "ReturnTypes": []
  },
  {
    "ContainingType": "ApiQUIZZ.Controllers.AlternativasController",
    "Method": "DeleteAlternativa",
    "RelativePath": "api/Alternativas/{id}",
    "HttpMethod": "DELETE",
    "IsController": true,
    "Order": 0,
    "Parameters": [
      {
        "Name": "id",
        "Type": "System.Int32",
        "IsRequired": true
      }
    ],
    "ReturnTypes": []
  },
  {
    "ContainingType": "ApiQUIZZ.Controllers.DisciplinasController",
    "Method": "GetDisciplinas",
    "RelativePath": "api/Disciplinas",
    "HttpMethod": "GET",
    "IsController": true,
    "Order": 0,
    "Parameters": [],
    "ReturnTypes": [
      {
        "Type": "System.Collections.Generic.IEnumerable\u00601[[ApiQUIZZ.Models.Disciplina, ApiQUIZZ, Version=1.0.0.0, Culture=neutral, PublicKeyToken=null]]",
        "MediaTypes": [
          "text/plain",
          "application/json",
          "text/json"
        ],
        "StatusCode": 200
      }
    ]
  },
  {
    "ContainingType": "ApiQUIZZ.Controllers.DisciplinasController",
    "Method": "PostDisciplina",
    "RelativePath": "api/Disciplinas",
    "HttpMethod": "POST",
    "IsController": true,
    "Order": 0,
    "Parameters": [
      {
        "Name": "disciplina",
        "Type": "ApiQUIZZ.Models.Disciplina",
        "IsRequired": true
      }
    ],
    "ReturnTypes": [
      {
        "Type": "ApiQUIZZ.Models.Disciplina",
        "MediaTypes": [
          "text/plain",
          "application/json",
          "text/json"
        ],
        "StatusCode": 200
      }
    ]
  },
  {
    "ContainingType": "ApiQUIZZ.Controllers.DisciplinasController",
    "Method": "GetDisciplina",
    "RelativePath": "api/Disciplinas/{id}",
    "HttpMethod": "GET",
    "IsController": true,
    "Order": 0,
    "Parameters": [
      {
        "Name": "id",
        "Type": "System.Int32",
        "IsRequired": true
      }
    ],
    "ReturnTypes": [
      {
        "Type": "ApiQUIZZ.Models.Disciplina",
        "MediaTypes": [
          "text/plain",
          "application/json",
          "text/json"
        ],
        "StatusCode": 200
      }
    ]
  },
  {
    "ContainingType": "ApiQUIZZ.Controllers.DisciplinasController",
    "Method": "PutDisciplina",
    "RelativePath": "api/Disciplinas/{id}",
    "HttpMethod": "PUT",
    "IsController": true,
    "Order": 0,
    "Parameters": [
      {
        "Name": "id",
        "Type": "System.Int32",
        "IsRequired": true
      },
      {
        "Name": "disciplina",
        "Type": "ApiQUIZZ.Models.Disciplina",
        "IsRequired": true
      }
    ],
    "ReturnTypes": []
  },
  {
    "ContainingType": "ApiQUIZZ.Controllers.DisciplinasController",
    "Method": "DeleteDisciplina",
    "RelativePath": "api/Disciplinas/{id}",
    "HttpMethod": "DELETE",
    "IsController": true,
    "Order": 0,
    "Parameters": [
      {
        "Name": "id",
        "Type": "System.Int32",
        "IsRequired": true
      }
    ],
    "ReturnTypes": []
  },
  {
    "ContainingType": "ApiQUIZZ.Controllers.NotasController",
    "Method": "GetNotas",
    "RelativePath": "api/Notas",
    "HttpMethod": "GET",
    "IsController": true,
    "Order": 0,
    "Parameters": [],
    "ReturnTypes": [
      {
        "Type": "System.Collections.Generic.IEnumerable\u00601[[ApiQUIZZ.Models.Nota, ApiQUIZZ, Version=1.0.0.0, Culture=neutral, PublicKeyToken=null]]",
        "MediaTypes": [
          "text/plain",
          "application/json",
          "text/json"
        ],
        "StatusCode": 200
      }
    ]
  },
  {
    "ContainingType": "ApiQUIZZ.Controllers.NotasController",
    "Method": "PostNota",
    "RelativePath": "api/Notas",
    "HttpMethod": "POST",
    "IsController": true,
    "Order": 0,
    "Parameters": [
      {
        "Name": "nota",
        "Type": "ApiQUIZZ.Models.Nota",
        "IsRequired": true
      }
    ],
    "ReturnTypes": [
      {
        "Type": "ApiQUIZZ.Models.Nota",
        "MediaTypes": [
          "text/plain",
          "application/json",
          "text/json"
        ],
        "StatusCode": 200
      }
    ]
  },
  {
    "ContainingType": "ApiQUIZZ.Controllers.NotasController",
    "Method": "GetNota",
    "RelativePath": "api/Notas/{id}",
    "HttpMethod": "GET",
    "IsController": true,
    "Order": 0,
    "Parameters": [
      {
        "Name": "id",
        "Type": "System.Int32",
        "IsRequired": true
      }
    ],
    "ReturnTypes": [
      {
        "Type": "ApiQUIZZ.Models.Nota",
        "MediaTypes": [
          "text/plain",
          "application/json",
          "text/json"
        ],
        "StatusCode": 200
      }
    ]
  },
  {
    "ContainingType": "ApiQUIZZ.Controllers.NotasController",
    "Method": "PutNota",
    "RelativePath": "api/Notas/{id}",
    "HttpMethod": "PUT",
    "IsController": true,
    "Order": 0,
    "Parameters": [
      {
        "Name": "id",
        "Type": "System.Int32",
        "IsRequired": true
      },
      {
        "Name": "nota",
        "Type": "ApiQUIZZ.Models.Nota",
        "IsRequired": true
      }
    ],
    "ReturnTypes": []
  },
  {
    "ContainingType": "ApiQUIZZ.Controllers.NotasController",
    "Method": "DeleteNota",
    "RelativePath": "api/Notas/{id}",
    "HttpMethod": "DELETE",
    "IsController": true,
    "Order": 0,
    "Parameters": [
      {
        "Name": "id",
        "Type": "System.Int32",
        "IsRequired": true
      }
    ],
    "ReturnTypes": []
  },
  {
    "ContainingType": "ApiQUIZZ.Controllers.PerguntasController",
    "Method": "GetPerguntas",
    "RelativePath": "api/Perguntas",
    "HttpMethod": "GET",
    "IsController": true,
    "Order": 0,
    "Parameters": [],
    "ReturnTypes": [
      {
        "Type": "System.Collections.Generic.IEnumerable\u00601[[ApiQUIZZ.Models.Pergunta, ApiQUIZZ, Version=1.0.0.0, Culture=neutral, PublicKeyToken=null]]",
        "MediaTypes": [
          "text/plain",
          "application/json",
          "text/json"
        ],
        "StatusCode": 200
      }
    ]
  },
  {
    "ContainingType": "ApiQUIZZ.Controllers.PerguntasController",
    "Method": "PostPergunta",
    "RelativePath": "api/Perguntas",
    "HttpMethod": "POST",
    "IsController": true,
    "Order": 0,
    "Parameters": [
      {
        "Name": "pergunta",
        "Type": "ApiQUIZZ.Models.Pergunta",
        "IsRequired": true
      }
    ],
    "ReturnTypes": [
      {
        "Type": "ApiQUIZZ.Models.Pergunta",
        "MediaTypes": [
          "text/plain",
          "application/json",
          "text/json"
        ],
        "StatusCode": 200
      }
    ]
  },
  {
    "ContainingType": "ApiQUIZZ.Controllers.PerguntasController",
    "Method": "GetPergunta",
    "RelativePath": "api/Perguntas/{id}",
    "HttpMethod": "GET",
    "IsController": true,
    "Order": 0,
    "Parameters": [
      {
        "Name": "id",
        "Type": "System.Int32",
        "IsRequired": true
      }
    ],
    "ReturnTypes": [
      {
        "Type": "ApiQUIZZ.Models.Pergunta",
        "MediaTypes": [
          "text/plain",
          "application/json",
          "text/json"
        ],
        "StatusCode": 200
      }
    ]
  },
  {
    "ContainingType": "ApiQUIZZ.Controllers.PerguntasController",
    "Method": "PutPergunta",
    "RelativePath": "api/Perguntas/{id}",
    "HttpMethod": "PUT",
    "IsController": true,
    "Order": 0,
    "Parameters": [
      {
        "Name": "id",
        "Type": "System.Int32",
        "IsRequired": true
      },
      {
        "Name": "pergunta",
        "Type": "ApiQUIZZ.Models.Pergunta",
        "IsRequired": true
      }
    ],
    "ReturnTypes": []
  },
  {
    "ContainingType": "ApiQUIZZ.Controllers.PerguntasController",
    "Method": "DeletePergunta",
    "RelativePath": "api/Perguntas/{id}",
    "HttpMethod": "DELETE",
    "IsController": true,
    "Order": 0,
    "Parameters": [
      {
        "Name": "id",
        "Type": "System.Int32",
        "IsRequired": true
      }
    ],
    "ReturnTypes": []
  },
  {
    "ContainingType": "ApiQUIZZ.Controllers.QuizsController",
    "Method": "GetQuizzes",
    "RelativePath": "api/Quizs",
    "HttpMethod": "GET",
    "IsController": true,
    "Order": 0,
    "Parameters": [],
    "ReturnTypes": [
      {
        "Type": "System.Collections.Generic.IEnumerable\u00601[[ApiQUIZZ.Models.Quiz, ApiQUIZZ, Version=1.0.0.0, Culture=neutral, PublicKeyToken=null]]",
        "MediaTypes": [
          "text/plain",
          "application/json",
          "text/json"
        ],
        "StatusCode": 200
      }
    ]
  },
  {
    "ContainingType": "ApiQUIZZ.Controllers.QuizsController",
    "Method": "PostQuiz",
    "RelativePath": "api/Quizs",
    "HttpMethod": "POST",
    "IsController": true,
    "Order": 0,
    "Parameters": [
      {
        "Name": "quiz",
        "Type": "ApiQUIZZ.Models.Quiz",
        "IsRequired": true
      }
    ],
    "ReturnTypes": [
      {
        "Type": "ApiQUIZZ.Models.Quiz",
        "MediaTypes": [
          "text/plain",
          "application/json",
          "text/json"
        ],
        "StatusCode": 200
      }
    ]
  },
  {
    "ContainingType": "ApiQUIZZ.Controllers.QuizsController",
    "Method": "GetQuiz",
    "RelativePath": "api/Quizs/{id}",
    "HttpMethod": "GET",
    "IsController": true,
    "Order": 0,
    "Parameters": [
      {
        "Name": "id",
        "Type": "System.Int32",
        "IsRequired": true
      }
    ],
    "ReturnTypes": [
      {
        "Type": "ApiQUIZZ.Models.Quiz",
        "MediaTypes": [
          "text/plain",
          "application/json",
          "text/json"
        ],
        "StatusCode": 200
      }
    ]
  },
  {
    "ContainingType": "ApiQUIZZ.Controllers.QuizsController",
    "Method": "PutQuiz",
    "RelativePath": "api/Quizs/{id}",
    "HttpMethod": "PUT",
    "IsController": true,
    "Order": 0,
    "Parameters": [
      {
        "Name": "id",
        "Type": "System.Int32",
        "IsRequired": true
      },
      {
        "Name": "quiz",
        "Type": "ApiQUIZZ.Models.Quiz",
        "IsRequired": true
      }
    ],
    "ReturnTypes": []
  },
  {
    "ContainingType": "ApiQUIZZ.Controllers.QuizsController",
    "Method": "DeleteQuiz",
    "RelativePath": "api/Quizs/{id}",
    "HttpMethod": "DELETE",
    "IsController": true,
    "Order": 0,
    "Parameters": [
      {
        "Name": "id",
        "Type": "System.Int32",
        "IsRequired": true
      }
    ],
    "ReturnTypes": []
  },
  {
    "ContainingType": "ApiQUIZZ.Controllers.RespostasController",
    "Method": "GetRespostas",
    "RelativePath": "api/Respostas",
    "HttpMethod": "GET",
    "IsController": true,
    "Order": 0,
    "Parameters": [],
    "ReturnTypes": [
      {
        "Type": "System.Collections.Generic.IEnumerable\u00601[[ApiQUIZZ.Models.Resposta, ApiQUIZZ, Version=1.0.0.0, Culture=neutral, PublicKeyToken=null]]",
        "MediaTypes": [
          "text/plain",
          "application/json",
          "text/json"
        ],
        "StatusCode": 200
      }
    ]
  },
  {
    "ContainingType": "ApiQUIZZ.Controllers.RespostasController",
    "Method": "PostResposta",
    "RelativePath": "api/Respostas",
    "HttpMethod": "POST",
    "IsController": true,
    "Order": 0,
    "Parameters": [
      {
        "Name": "resposta",
        "Type": "ApiQUIZZ.Models.Resposta",
        "IsRequired": true
      }
    ],
    "ReturnTypes": [
      {
        "Type": "ApiQUIZZ.Models.Resposta",
        "MediaTypes": [
          "text/plain",
          "application/json",
          "text/json"
        ],
        "StatusCode": 200
      }
    ]
  },
  {
    "ContainingType": "ApiQUIZZ.Controllers.RespostasController",
    "Method": "GetResposta",
    "RelativePath": "api/Respostas/{id}",
    "HttpMethod": "GET",
    "IsController": true,
    "Order": 0,
    "Parameters": [
      {
        "Name": "id",
        "Type": "System.Int32",
        "IsRequired": true
      }
    ],
    "ReturnTypes": [
      {
        "Type": "ApiQUIZZ.Models.Resposta",
        "MediaTypes": [
          "text/plain",
          "application/json",
          "text/json"
        ],
        "StatusCode": 200
      }
    ]
  },
  {
    "ContainingType": "ApiQUIZZ.Controllers.RespostasController",
    "Method": "PutResposta",
    "RelativePath": "api/Respostas/{id}",
    "HttpMethod": "PUT",
    "IsController": true,
    "Order": 0,
    "Parameters": [
      {
        "Name": "id",
        "Type": "System.Int32",
        "IsRequired": true
      },
      {
        "Name": "resposta",
        "Type": "ApiQUIZZ.Models.Resposta",
        "IsRequired": true
      }
    ],
    "ReturnTypes": []
  },
  {
    "ContainingType": "ApiQUIZZ.Controllers.RespostasController",
    "Method": "DeleteResposta",
    "RelativePath": "api/Respostas/{id}",
    "HttpMethod": "DELETE",
    "IsController": true,
    "Order": 0,
    "Parameters": [
      {
        "Name": "id",
        "Type": "System.Int32",
        "IsRequired": true
      }
    ],
    "ReturnTypes": []
  },
  {
    "ContainingType": "ApiQUIZZ.Controllers.TurmasController",
    "Method": "GetTurmas",
    "RelativePath": "api/Turmas",
    "HttpMethod": "GET",
    "IsController": true,
    "Order": 0,
    "Parameters": [],
    "ReturnTypes": [
      {
        "Type": "System.Collections.Generic.IEnumerable\u00601[[ApiQUIZZ.Models.Turma, ApiQUIZZ, Version=1.0.0.0, Culture=neutral, PublicKeyToken=null]]",
        "MediaTypes": [
          "text/plain",
          "application/json",
          "text/json"
        ],
        "StatusCode": 200
      }
    ]
  },
  {
    "ContainingType": "ApiQUIZZ.Controllers.TurmasController",
    "Method": "PostTurma",
    "RelativePath": "api/Turmas",
    "HttpMethod": "POST",
    "IsController": true,
    "Order": 0,
    "Parameters": [
      {
        "Name": "turma",
        "Type": "ApiQUIZZ.Models.Turma",
        "IsRequired": true
      }
    ],
    "ReturnTypes": [
      {
        "Type": "ApiQUIZZ.Models.Turma",
        "MediaTypes": [
          "text/plain",
          "application/json",
          "text/json"
        ],
        "StatusCode": 200
      }
    ]
  },
  {
    "ContainingType": "ApiQUIZZ.Controllers.TurmasController",
    "Method": "GetTurma",
    "RelativePath": "api/Turmas/{id}",
    "HttpMethod": "GET",
    "IsController": true,
    "Order": 0,
    "Parameters": [
      {
        "Name": "id",
        "Type": "System.Int32",
        "IsRequired": true
      }
    ],
    "ReturnTypes": [
      {
        "Type": "ApiQUIZZ.Models.Turma",
        "MediaTypes": [
          "text/plain",
          "application/json",
          "text/json"
        ],
        "StatusCode": 200
      }
    ]
  },
  {
    "ContainingType": "ApiQUIZZ.Controllers.TurmasController",
    "Method": "PutTurma",
    "RelativePath": "api/Turmas/{id}",
    "HttpMethod": "PUT",
    "IsController": true,
    "Order": 0,
    "Parameters": [
      {
        "Name": "id",
        "Type": "System.Int32",
        "IsRequired": true
      },
      {
        "Name": "turma",
        "Type": "ApiQUIZZ.Models.Turma",
        "IsRequired": true
      }
    ],
    "ReturnTypes": []
  },
  {
    "ContainingType": "ApiQUIZZ.Controllers.TurmasController",
    "Method": "DeleteTurma",
    "RelativePath": "api/Turmas/{id}",
    "HttpMethod": "DELETE",
    "IsController": true,
    "Order": 0,
    "Parameters": [
      {
        "Name": "id",
        "Type": "System.Int32",
        "IsRequired": true
      }
    ],
    "ReturnTypes": []
  },
  {
    "ContainingType": "ApiQUIZZ.Controllers.UsuariosController",
    "Method": "GetUsuarios",
    "RelativePath": "api/Usuarios",
    "HttpMethod": "GET",
    "IsController": true,
    "Order": 0,
    "Parameters": [],
    "ReturnTypes": [
      {
        "Type": "System.Collections.Generic.IEnumerable\u00601[[ApiQUIZZ.Models.Usuario, ApiQUIZZ, Version=1.0.0.0, Culture=neutral, PublicKeyToken=null]]",
        "MediaTypes": [
          "text/plain",
          "application/json",
          "text/json"
        ],
        "StatusCode": 200
      }
    ]
  },
  {
    "ContainingType": "ApiQUIZZ.Controllers.UsuariosController",
    "Method": "PostUsuario",
    "RelativePath": "api/Usuarios",
    "HttpMethod": "POST",
    "IsController": true,
    "Order": 0,
    "Parameters": [
      {
        "Name": "usuario",
        "Type": "ApiQUIZZ.Models.Usuario",
        "IsRequired": true
      }
    ],
    "ReturnTypes": [
      {
        "Type": "ApiQUIZZ.Models.Usuario",
        "MediaTypes": [
          "text/plain",
          "application/json",
          "text/json"
        ],
        "StatusCode": 200
      }
    ]
  },
  {
    "ContainingType": "ApiQUIZZ.Controllers.UsuariosController",
    "Method": "GetUsuario",
    "RelativePath": "api/Usuarios/{id}",
    "HttpMethod": "GET",
    "IsController": true,
    "Order": 0,
    "Parameters": [
      {
        "Name": "id",
        "Type": "System.Int32",
        "IsRequired": true
      }
    ],
    "ReturnTypes": [
      {
        "Type": "ApiQUIZZ.Models.Usuario",
        "MediaTypes": [
          "text/plain",
          "application/json",
          "text/json"
        ],
        "StatusCode": 200
      }
    ]
  },
  {
    "ContainingType": "ApiQUIZZ.Controllers.UsuariosController",
    "Method": "PutUsuario",
    "RelativePath": "api/Usuarios/{id}",
    "HttpMethod": "PUT",
    "IsController": true,
    "Order": 0,
    "Parameters": [
      {
        "Name": "id",
        "Type": "System.Int32",
        "IsRequired": true
      },
      {
        "Name": "usuario",
        "Type": "ApiQUIZZ.Models.Usuario",
        "IsRequired": true
      }
    ],
    "ReturnTypes": []
  },
  {
    "ContainingType": "ApiQUIZZ.Controllers.UsuariosController",
    "Method": "DeleteUsuario",
    "RelativePath": "api/Usuarios/{id}",
    "HttpMethod": "DELETE",
    "IsController": true,
    "Order": 0,
    "Parameters": [
      {
        "Name": "id",
        "Type": "System.Int32",
        "IsRequired": true
      }
    ],
    "ReturnTypes": []
  }
]